orange3_regressionwidgets-0.1.7-py3.13-nspkg.pth
orangecontrib/regressionsummary/__init__.py
orangecontrib/regressionsummary/widgets/OWBackwardElimination.py
orangecontrib/regressionsummary/widgets/OWRegressionSummary.py
orangecontrib/regressionsummary/widgets/__init__.py
orangecontrib/regressionsummary/widgets/widgets.json
orangecontrib/regressionsummary/widgets/icons/RegressionSummary.svg
orangecontrib/regressionsummary/widgets/icons/backward_elimination.svg
orangecontrib/regressionsummary/widgets/icons/category.svg
orange3_regressionwidgets-0.1.7.dist-info/METADATA
orange3_regressionwidgets-0.1.7.dist-info/WHEEL
orange3_regressionwidgets-0.1.7.dist-info/entry_points.txt
orange3_regressionwidgets-0.1.7.dist-info/namespace_packages.txt
orange3_regressionwidgets-0.1.7.dist-info/top_level.txt
orange3_regressionwidgets-0.1.7.dist-info/RECORD
